nostr_agent_tools-0.5.0.dist-info/licenses/LICENSE
nostr_agents/__init__.py
nostr_agents/nostr_agent_server.py
nostr_agents/nostr_client.py
nostr_agents/nostr_mcp_client.py
nostr_agents/nostr_mcp_server.py
nostr_agents/nwc.py
nostr_agents/nwc_client.py
nostr_agent_tools-0.5.0.dist-info/METADATA
nostr_agent_tools-0.5.0.dist-info/WHEEL
nostr_agent_tools-0.5.0.dist-info/top_level.txt
nostr_agent_tools-0.5.0.dist-info/RECORD
